cardy/__init__.py
cardy/clique.py
cardy/distance.py
cardy/neighbourhood.py
cardy/orthogonality.py
cardy/types.py
cardy-0.3.3.dist-info/licenses/LICENSE
cardy-0.3.3.dist-info/METADATA
cardy-0.3.3.dist-info/WHEEL
cardy-0.3.3.dist-info/top_level.txt
cardy-0.3.3.dist-info/RECORD
