Metadata-Version: 2.4
Name: cardy
Version: 0.3.3
Summary: Card Sorting Utilities
License-Expression: Apache-2.0
Project-URL: repository, https://codeberg.org/jamesansley/cardy
Requires-Python: >=3.12
License-File: LICENSE
Requires-Dist: munkres~=1.1.4
Dynamic: license-file
